labelgun/__init__.py
labelgun/integrations/__init__.py
labelgun/integrations/logging_utils.py
labelgun/integrations/structlog_utils.py
labelgun/label.py
labelgun-0.2.1.dist-info/LICENSE
labelgun-0.2.1.dist-info/WHEEL
labelgun-0.2.1.dist-info/METADATA
labelgun-0.2.1.dist-info/RECORD
