Metadata-Version: 2.1
Name: labelgun
Version: 0.2.1
Summary: Library to define system events
License: MIT
Author: Aleksey Petrunnik
Author-email: apetrunnik@usetech.com
Requires-Python: >=3.6,<4.0
Classifier: License :: OSI Approved :: MIT License
Classifier: Programming Language :: Python :: 3
Classifier: Programming Language :: Python :: 3.6
Classifier: Programming Language :: Python :: 3.7
Classifier: Programming Language :: Python :: 3.8
Classifier: Programming Language :: Python :: 3.9
Classifier: Programming Language :: Python :: 3.10
Classifier: Programming Language :: Python :: 3.11
Provides-Extra: logger
Requires-Dist: aenum (>=3.0.0,<4.0.0)
Requires-Dist: python-json-logger (>=2.0,<2.1); extra == "logger"
Requires-Dist: structlog (>=20,<22); extra == "logger"
